<?xml version='1.0' encoding='UTF-8'?>
<Drawable>
  <Name>lavender</Name>
  <BoundingSphereCenter x="-0.011791557" y="0.003012985" z="0.06325646" />
  <BoundingSphereRadius value="0.9723909" />
  <BoundingBoxMin x="-0.6023954" y="-0.575938" z="-0.44816014" />
  <BoundingBoxMax x="0.5788123" y="0.58196396" z="0.57467306" />
  <LodDistHigh value="9998" />
  <LodDistMed value="9998" />
  <LodDistLow value="9998" />
  <LodDistVlow value="9998" />
  <FlagsHigh value="1" />
  <FlagsMed value="0" />
  <FlagsLow value="0" />
  <FlagsVlow value="0" />
  <Unknown9A value="9998" />
  <ShaderGroup>
    <Unknown30 value="0" />
    <Shaders>
      <Item>
        <Name>cutout_fence</Name>
        <FileName>cutout_fence.sps</FileName>
        <RenderBucket value="3" />
        <Parameters>
          <Item name="DiffuseSampler" type="Texture">
            <Name>lavender</Name>
          </Item>
          <Item name="hardalphablend" type="Vector" x="0.0" y="0.0" z="0.0" w="0.0" />
          <Item name="usetessellation" type="Vector" x="0.0" y="0.0" z="0.0" w="0.0" />
        </Parameters>
      </Item>
    </Shaders>
  </ShaderGroup>
  <DrawableModelsHigh>
    <Item>
      <RenderMask value="255" />
      <Flags value="0" />
      <HasSkin value="0" />
      <BoneIndex value="0" />
      <Unknown1 value="0" />
      <Geometries>
        <Item>
          <ShaderIndex value="0" />
          <BoundingBoxMin x="-0.6023954" y="-0.575938" z="-0.44816014" />
          <BoundingBoxMax x="0.5788123" y="0.58196396" z="0.57467306" />
          <BoneIDs />
          <VertexBuffer>
            <Flags value="0" />
            <Layout type="GTAV1">
              <Position />
              <Normal />
              <Colour0 />
              <TexCoord0 />
            </Layout>
            <Data>
              0.25334388 -0.32755294 -0.052497752   1.357842 1.1549695 -0.04768248   255 0 77 255   0.11349821 0.28792852   
              0.27988628 -0.3651324 -0.20691857   1.3578595 1.1549493 -0.04767178   255 0 77 255   0.061131537 0.59921926   
              0.14246243 -0.20446835 -0.22864966   1.3578321 1.1549809 -0.047690045   255 0 77 255   0.24732429 0.6690415   
              -0.20838448 0.20990165 -0.1825578   1.3578383 1.154974 -0.047683027   255 0 77 255   0.7331709 0.6690415   
              -0.34035468 0.36946416 -0.07570568   1.3578432 1.1549683 -0.047680043   255 0 77 255   0.9251821 0.51194143   
              -0.25407135 0.27344558 0.055605046   1.3578352 1.1549773 -0.04768408   255 0 77 255   0.82044864 0.21519685   
              -0.00041233655 -0.043511488 -0.39845917   1.3578368 1.1549754 -0.04768668   255 0 77 255   0.425674 1.0   
              -0.08513273 0.075560406 0.073195964   1.3578327 1.1549805 -0.04768619   255 0 77 255   0.59061706 0.14537466   
              0.05995536 -0.09456169 0.083973415   1.3578292 1.1549844 -0.04768887   255 0 77 255   0.39278737 0.09300792   
              -0.10390904 0.07872409 -0.38486263   1.3578345 1.1549784 -0.047681928   255 0 77 255   0.5689946 1.0   
              -0.1859716 0.19582237 0.114624254   1.3578373 1.1549747 -0.04768748   255 0 77 255   0.73317087 0.095917225   
              0.05334659 -0.103189215 -0.3130883   1.357846 1.1549641 -0.047695838   255 0 77 255   0.36078548 0.8377786   
              0.21474458 0.14940599 -0.088305876   -0.8914927 1.5380433 0.14009571   255 0 77 255   0.24732429 0.6690415   
              0.41425833 0.25612503 0.009680234   -0.8914975 1.53804 0.14010088   255 0 77 255   0.04949457 0.55558026   
              0.399887 0.25149947 -0.030984798   -0.8915031 1.5380354 0.14011697   255 0 77 255   0.061131537 0.59921926   
              -0.25539815 -0.12514901 -0.06585646   -0.8914928 1.5380417 0.14011098   255 0 77 255   0.7331709 0.6690415   
              -0.4300182 -0.24068215 0.09134697   -0.8914752 1.5380517 0.14011492   255 0 77 255   0.9251821 0.51194143   
              -0.30753684 -0.19477352 0.36668685   -0.89152026 1.5380265 0.14010538   255 0 77 255   0.82044864 0.21519685   
              0.018593712 0.06342298 -0.3925494   -0.8914854 1.5380464 0.1401065   255 0 77 255   0.425674 1.0   
              -0.08016447 -0.068019725 0.42199185   -0.8915 1.5380386 0.14010043   255 0 77 255   0.59061706 0.14537466   
              0.11499994 0.041438982 0.46229446   -0.89151746 1.5380287 0.14009595   255 0 77 255   0.39278737 0.09300792   
              -0.120097116 -0.017566347 -0.38592654   -0.8914741 1.5380526 0.14011174   255 0 77 255   0.5689946 1.0   
              -0.21458703 -0.15078561 0.47527558   -0.89149207 1.538043 0.14010075   255 0 77 255   0.73317087 0.095917225   
              0.37138262 0.20798525 0.26534888   -0.891496 1.5380415 0.1400937   255 0 77 255   0.11349821 0.28792852   
              0.092934474 0.09283599 -0.24238159   -0.8915099 1.5380334 0.14009546   255 0 77 255   0.36078548 0.8377786   
              -0.12547666 -0.2803193 -0.08587977   1.549146 0.85670185 -0.21487536   255 0 77 255   0.24732429 0.6690415   
              0.003766654 -0.49109307 0.0055521475   1.5395564 0.89173764 -0.12055336   255 0 77 255   0.04949457 0.55558026   
              0.0007917793 -0.47610357 -0.0350431   1.4499832 1.0037978 0.26438946   255 0 77 255   0.061131537 0.59921926   
              -0.027110053 0.26783264 -0.06445511   1.7781142 -0.011811024 -0.13465627   255 0 77 255   0.7331709 0.6690415   
              -0.013735612 0.47591236 0.09390113   1.7781142 -0.011811024 -0.13465627   255 0 77 255   0.9251821 0.51194143   
              0.0062007215 0.34530756 0.3686128   1.7781142 -0.011811024 -0.13465627   255 0 77 255   0.82044864 0.21519685   
              -0.054178365 -0.0618466 -0.39299583   1.778114 -0.011803283 -0.13466328   255 0 77 255   0.425674 1.0   
              0.008557798 0.08470781 0.4225362   1.7781138 -0.011820093 -0.13466026   255 0 77 255   0.59061706 0.14537466   
              0.0100308275 -0.13925923 0.46165028   1.7781138 -0.011822683 -0.13465981   255 0 77 255   0.39278737 0.09300792   
              -0.027110053 0.26783264 -0.06445511   1.7750071 -0.069896646 -0.15628722   255 0 77 255   0.7331709 0.6690415   
              0.008557798 0.08470781 0.4225362   1.7163976 -0.3977087 -0.27526277   255 0 77 255   0.59061706 0.14537466   
              -0.052546125 0.098714806 -0.38551217   1.778114 -0.01178746 -0.13466378   255 0 77 255   0.5689946 1.0   
              0.06337332 0.24235763 0.47941786   1.6423982 0.65081364 -0.2427594   255 0 77 255   0.73317087 0.095917225   
              -0.027110053 0.26783264 -0.06445511   1.6423982 0.65081364 -0.2427594   255 0 77 255   0.7331709 0.6690415   
              0.0062007215 0.34530756 0.3686128   1.6423982 0.65081364 -0.2427594   255 0 77 255   0.82044864 0.21519685   
              0.0100308275 -0.13925923 0.46165028   1.6501113 0.4323571 -0.51977205   255 0 77 255   0.39278737 0.09300792   
              0.023554252 -0.43136245 0.2616053   1.6501113 0.4323571 -0.51977205   255 0 77 255   0.11349821 0.28792852   
              -0.12547666 -0.2803193 -0.08587977   1.6501113 0.4323571 -0.51977205   255 0 77 255   0.24732429 0.6690415   
              0.0100308275 -0.13925923 0.46165028   1.5980551 -0.7824317 -0.118246675   255 0 77 255   0.39278737 0.09300792   
              -0.04336542 -0.14179213 -0.24321784   1.7596484 -0.25705242 -0.13237587   255 0 77 255   0.36078548 0.8377786   
              -0.054178365 -0.0618466 -0.39299583   1.7781146 -0.011781193 -0.1346561   255 0 77 255   0.425674 1.0   
              0.08139373 0.26726377 -0.0726652   -1.6348534 0.69484556 0.15622775   255 0 77 255   0.24732429 0.6690415   
              0.17650658 0.46625942 0.037566308   -1.634852 0.69483966 0.15626535   255 0 77 255   0.04949457 0.55558026   
              0.16827774 0.45621115 -0.003818886   -1.6348649 0.6947846 0.15637566   255 0 77 255   0.061131537 0.59921926   
              -0.13233992 -0.23391081 -0.08028995   -1.6348642 0.69482356 0.15621118   255 0 77 255   0.7331709 0.6690415   
              -0.2056257 -0.43900752 0.0650279   -1.6348572 0.694843 0.15619703   255 0 77 255   0.9251821 0.51194143   
              -0.14172661 -0.34216735 0.3030425   -1.6348336 0.6948949 0.15621226   255 0 77 255   0.82044864 0.21519685   
              -0.020635277 0.09809167 -0.38794836   -1.6348565 0.69483984 0.15621822   255 0 77 255   0.425674 1.0   
              -0.035645418 -0.10820864 0.37257347   -1.6348597 0.69483215 0.15621857   255 0 77 255   0.59061706 0.14537466   
              0.055117078 0.09352009 0.42512122   -1.6348503 0.6948531 0.1562233   255 0 77 255   0.39278737 0.09300792   
              -0.08368532 -0.049751285 -0.39019743   -1.6348611 0.6948297 0.1562153   255 0 77 255   0.5689946 1.0   
              -0.09483288 -0.2574719 0.41703272   -1.6348549 0.6948442 0.15621619   255 0 77 255   0.73317087 0.095917225   
              0.16410354 0.3903409 0.24546391   -1.634852 0.69485015 0.15622003   255 0 77 255   0.11349821 0.28792852   
              0.019463535 0.15777262 -0.23376413   -1.6348561 0.69483936 0.1562238   255 0 77 255   0.36078548 0.8377786   
              0.09257104 -0.2481181 -0.09792538   1.6029289 0.77686024 -0.08408345   255 0 77 255   0.24732429 0.6690415   
              0.19643448 -0.4526337 -0.0074705295   1.6029276 0.77686346 -0.08407467   255 0 77 255   0.04949457 0.55558026   
              0.18769372 -0.4389498 -0.047692783   1.6029224 0.7768787 -0.084035255   255 0 77 255   0.061131537 0.59921926   
              -0.14266053 0.24168655 -0.05697921   1.6924746 0.46796778 0.31064168   255 0 77 255   0.7331709 0.6690415   
              -0.2244364 0.42823622 0.10753307   1.6924746 0.46796778 0.31064168   255 0 77 255   0.9251821 0.51194143   
              -0.22449507 0.25145215 0.37416995   1.6924746 0.46796778 0.31064168   255 0 77 255   0.82044864 0.21519685   
              -0.01734519 -0.05351065 -0.39537877   1.5851614 0.8118693 -0.08996171   255 0 77 255   0.425674 1.0   
              -0.036348835 0.07454722 0.4254416   1.4933299 0.96766794 -0.116394244   255 0 77 255   0.59061706 0.14537466   
              0.085709535 -0.10323166 0.46273953   1.4784273 0.9898326 -0.12019724   255 0 77 255   0.39278737 0.09300792   
              -0.14266053 0.24168655 -0.05697921   1.5544708 0.8729108 -0.040132336   255 0 77 255   0.7331709 0.6690415   
              -0.036348835 0.07454722 0.4254416   1.1309206 1.3607358 0.22221752   255 0 77 255   0.59061706 0.14537466   
              -0.086736195 0.09097972 -0.3833001   1.6029222 0.77687407 -0.084082514   255 0 77 255   0.5689946 1.0   
              -0.17374076 0.15812692 0.47943512   1.4204057 1.0497531 0.2458239   255 0 77 255   0.73317087 0.095917225   
              -0.14266053 0.24168655 -0.05697921   1.4204057 1.0497531 0.2458239   255 0 77 255   0.7331709 0.6690415   
              -0.22449507 0.25145215 0.37416995   1.4204057 1.0497531 0.2458239   255 0 77 255   0.82044864 0.21519685   
              0.085709535 -0.10323166 0.46273953   1.6513224 0.65633583 -0.14940047   255 0 77 255   0.39278737 0.09300792   
              0.18450584 -0.40008122 0.2506351   1.6513224 0.65633583 -0.14940047   255 0 77 255   0.11349821 0.28792852   
              0.09257104 -0.2481181 -0.09792538   1.6513224 0.65633583 -0.14940047   255 0 77 255   0.24732429 0.6690415   
              0.085709535 -0.10323166 0.46273953   1.6384885 0.68519086 -0.16072114   255 0 77 255   0.39278737 0.09300792   
              0.025621248 -0.12618244 -0.24768116   1.6483612 0.6610741 -0.16077706   255 0 77 255   0.36078548 0.8377786   
              -0.01734519 -0.05351065 -0.39537877   1.6526349 0.65031296 -0.16079089   255 0 77 255   0.425674 1.0   
              0.19134094 -0.168874 -0.10162015   0.8929034 1.5433657 -0.02662908   255 0 77 255   0.24732429 0.6690415   
              0.38438794 -0.2790054 -0.011520755   0.8845468 1.5483972 -0.0025741328   255 0 77 255   0.04949457 0.55558026   
              0.37109715 -0.2689672 -0.05157257   0.8414825 1.5680963 0.1137746   255 0 77 255   0.061131537 0.59921926   
              -0.23380214 0.16855898 -0.053569973   0.9259981 1.5007359 -0.26510924   255 0 77 255   0.7331709 0.6690415   
              -0.39064026 0.29489034 0.11375046   0.9259981 1.5007359 -0.26510924   255 0 77 255   0.9251821 0.51194143   
              -0.25749648 0.26925713 0.43370232   0.9259981 1.5007359 -0.26510924   255 0 77 255   0.82044864 0.21519685   
              0.011709955 -0.030199943 -0.3964657   1.0287224 1.4560792 0.03907357   255 0 77 255   0.425674 1.0   
              -0.11346414 0.03513474 0.464396   0.6682879 1.6530441 -0.028284185   255 0 77 255   0.59061706 0.14537466   
              0.13379332 -0.054313842 0.50821406   0.6124524 1.6743417 -0.03801935   255 0 77 255   0.39278737 0.09300792   
              -0.23380214 0.16855898 -0.053569973   1.2400136 1.2808508 0.041847948   255 0 77 255   0.7331709 0.6690415   
              -0.11346414 0.03513474 0.464396   1.3999404 1.1038375 -0.04090485   255 0 77 255   0.59061706 0.14537466   
              -0.11370613 0.06933757 -0.38229138   1.2180877 1.3013449 0.052221064   255 0 77 255   0.5689946 1.0   
              -0.18949251 0.1407247 0.53395015   1.600645 0.7815975 -0.08368863   255 0 77 255   0.73317087 0.095917225   
              -0.23380214 0.16855898 -0.053569973   1.600645 0.7815975 -0.08368863   255 0 77 255   0.7331709 0.6690415   
              -0.25749648 0.26925713 0.43370232   1.600645 0.7815975 -0.08368863   255 0 77 255   0.82044864 0.21519685   
              0.13379332 -0.054313842 0.50821406   1.0947855 1.3985686 -0.159417   255 0 77 255   0.39278737 0.09300792   
              0.35093632 -0.24871889 0.29390928   1.0947855 1.3985686 -0.159417   255 0 77 255   0.11349821 0.28792852   
              0.19134094 -0.168874 -0.10162015   1.0947855 1.3985686 -0.159417   255 0 77 255   0.24732429 0.6690415   
              0.13379332 -0.054313842 0.50821406   1.2148066 1.2985083 -0.13448025   255 0 77 255   0.39278737 0.09300792   
              0.080040626 -0.08252129 -0.24971688   1.2434098 1.2710388 -0.13548647   255 0 77 255   0.36078548 0.8377786   
              0.011709955 -0.030199943 -0.3964657   1.255751 1.2588019 -0.13590628   255 0 77 255   0.425674 1.0   
              0.25214583 0.027201744 -0.096916676   -0.17572832 1.759911 0.22758946   255 0 77 255   0.24732429 0.6690415   
              0.48094532 0.03824787 -0.0056718295   -0.16551206 1.7640805 0.20146704   255 0 77 255   0.04949457 0.55558026   
              0.464855 0.039252207 -0.04593996   -0.12304709 1.7765375 0.09347637   255 0 77 255   0.061131537 0.59921926   
              -0.30953377 -0.046497244 -0.056037787   -0.12302576 1.7765408 0.09344251   255 0 77 255   0.7331709 0.6690415   
              -0.5125765 -0.06917086 0.107708536   -0.12302707 1.7765408 0.093442224   255 0 77 255   0.9251821 0.51194143   
              -0.3792953 -0.07095711 0.3171484   -0.12302351 1.7765408 0.093443014   255 0 77 255   0.82044864 0.21519685   
              0.029595178 0.027478334 -0.395082   -0.29456207 1.7576095 0.06328617   255 0 77 255   0.425674 1.0   
              -0.098278254 -0.02123942 0.3627478   -0.8757019 1.5526785 -0.04794742   255 0 77 255   0.59061706 0.14537466   
              0.11384563 0.11701598 0.3949321   -0.96590626 1.4975104 -0.06671469   255 0 77 255   0.39278737 0.09300792   
              -0.30953377 -0.046497244 -0.056037787   -0.4158003 1.7308881 0.1053562   255 0 77 255   0.7331709 0.6690415   
              -0.098278254 -0.02123942 0.3627478   -0.42838576 1.7274039 0.111915   255 0 77 255   0.59061706 0.14537466   
              -0.1303094 0.015797904 -0.38357568   -0.41251716 1.7317767 0.10364643   255 0 77 255   0.5689946 1.0   
              -0.27342355 -0.069180846 0.42276278   -0.12302226 1.7765409 0.09344329   255 0 77 255   0.73317087 0.095917225   
              0.11384563 0.11701598 0.3949321   0.53338677 1.6941254 -0.15937644   255 0 77 255   0.39278737 0.09300792   
              0.4142396 0.0029545194 0.18782316   0.53338677 1.6941254 -0.15937644   255 0 77 255   0.11349821 0.28792852   
              0.25214583 0.027201744 -0.096916676   0.53338677 1.6941254 -0.15937644   255 0 77 255   0.24732429 0.6690415   
              0.11384563 0.11701598 0.3949321   0.31187183 1.7381762 -0.24787739   255 0 77 255   0.39278737 0.09300792   
              0.11354283 0.025507921 -0.24712557   0.41958058 1.7158139 -0.24474101   255 0 77 255   0.36078548 0.8377786   
              0.029595178 0.027478334 -0.395082   0.4682625 1.7034218 -0.24299785   255 0 77 255   0.425674 1.0   
              0.14496699 0.40236205 -0.008275885   -1.6348495 0.69485205 0.15623757   255 0 77 255   0.11349821 0.28792852   
              0.1567321 0.46346387 -0.15690766   -1.6348175 0.6949196 0.15627249   255 0 77 255   0.061131537 0.59921926   
              0.071848914 0.27325958 -0.19922397   -1.6348547 0.6948415 0.15623035   255 0 77 255   0.24732429 0.6690415   
              -0.1418847 -0.227915 -0.20684819   -1.6348622 0.69482857 0.15620801   255 0 77 255   0.7331709 0.6690415   
              -0.21967249 -0.43018365 -0.121224456   -1.6348581 0.6948436 0.15618469   255 0 77 255   0.9251821 0.51194143   
              -0.16294743 -0.3288369 0.02166584   -1.6348383 0.69488555 0.15620494   255 0 77 255   0.82044864 0.21519685   
              -0.02069586 0.09812973 -0.38875166   -1.6348554 0.69484144 0.15622143   255 0 77 255   0.425674 1.0   
              -0.058867067 -0.0936213 0.06466678   -1.6348599 0.6948312 0.15621981   255 0 77 255   0.59061706 0.14537466   
              0.030394793 0.109050095 0.097317025   -1.6348503 0.6948521 0.1562282   255 0 77 255   0.39278737 0.09300792   
              -0.08374591 -0.049713228 -0.39100072   -1.6348617 0.6948279 0.15621482   255 0 77 255   0.5689946 1.0   
              -0.1194718 -0.24199426 0.090333864   -1.6348525 0.6948496 0.15621647   255 0 77 255   0.73317087 0.095917225   
              0.014754224 0.1607309 -0.29620692   -1.6348555 0.69483924 0.15622915   255 0 77 255   0.36078548 0.8377786   
              0.40580606 0.039814647 -0.04512386   -0.14214677 1.7750398 0.09482336   255 0 77 255   0.11349821 0.28792852   
              0.45291257 0.051794022 -0.19874878   -0.1421348 1.7750403 0.09483087   255 0 77 255   0.061131537 0.59921926   
              0.24237332 0.036245417 -0.22331335   -0.14216001 1.7750393 0.09481527   255 0 77 255   0.24732429 0.6690415   
              -0.29924884 -0.00919482 -0.18461804   -0.14213322 1.7750413 0.09481773   255 0 77 255   0.7331709 0.6690415   
              -0.50661683 -0.03135216 -0.080688685   -0.1421362 1.7750403 0.094830625   255 0 77 255   0.9251821 0.51194143   
              -0.37920892 -0.028250374 0.05221641   -0.14216143 1.7750387 0.094822004   255 0 77 255   0.82044864 0.21519685   
              0.029466713 0.028411184 -0.39583778   -0.14214472 1.7750405 0.094814226   255 0 77 255   0.425674 1.0   
              -0.12002233 -0.008621417 0.073305935   -0.14213994 1.7750407 0.0948156   255 0 77 255   0.59061706 0.14537466   
              0.102745794 0.00848242 0.08709543   -0.14215098 1.7750399 0.094816975   255 0 77 255   0.39278737 0.09300792   
              -0.1303067 0.01500473 -0.38442314   -0.14215492 1.7750398 0.09481443   255 0 77 255   0.5689946 1.0   
              -0.27683595 -0.023274085 0.11256402   -0.14214545 1.7750405 0.09481445   255 0 77 255   0.73317087 0.095917225   
              0.10870694 0.03014166 -0.30947942   -0.14211494 1.7750431 0.09480913   255 0 77 255   0.36078548 0.8377786   
              0.29014754 -0.37622684 -0.18340138   1.3578954 1.154908 -0.04765534   255 0 77 255   0.04949457 0.55558026   
              0.023554252 -0.43136245 0.2616053   1.5538112 0.81791794 -0.31087667   255 0 77 255   0.11349821 0.28792852   
              -0.052546125 0.098714806 -0.38551217   1.7781137 -0.011799428 -0.13466397   255 0 77 255   0.5689946 1.0   
              0.06337332 0.24235763 0.47941786   1.6908355 -0.47833017 -0.30370685   255 0 77 255   0.73317087 0.095917225   
              -0.12547666 -0.2803193 -0.08587977   1.4746188 -0.99688035 -0.108125314   255 0 77 255   0.24732429 0.6690415   
              0.18450584 -0.40008122 0.2506351   1.6029302 0.7768564 -0.08409306   255 0 77 255   0.11349821 0.28792852   
              -0.086736195 0.09097972 -0.3833001   1.6029406 0.77683586 -0.08408442   255 0 77 255   0.5689946 1.0   
              -0.17374076 0.15812692 0.47943512   0.995056 1.4523203 0.28388864   255 0 77 255   0.73317087 0.095917225   
              0.09257104 -0.2481181 -0.09792538   1.6326193 0.6990717 -0.16067313   255 0 77 255   0.24732429 0.6690415   
              0.35093632 -0.24871889 0.29390928   0.9020652 1.5373237 -0.053644516   255 0 77 255   0.11349821 0.28792852   
              -0.11370613 0.06933757 -0.38229138   1.1119046 1.3930186 0.055954657   255 0 77 255   0.5689946 1.0   
              -0.18949251 0.1407247 0.53395015   1.4283127 1.0661205 -0.057212133   255 0 77 255   0.73317087 0.095917225   
              0.19134094 -0.168874 -0.10162015   1.1978006 1.314275 -0.13386099   255 0 77 255   0.24732429 0.6690415   
              0.4142396 0.0029545194 0.18782316   -0.18670845 1.7549093 0.25572804   255 0 77 255   0.11349821 0.28792852   
              -0.1303094 0.015797904 -0.38357568   -0.1230456 1.7765392 0.093444124   255 0 77 255   0.5689946 1.0   
              -0.27342355 -0.069180846 0.42276278   -0.43323866 1.7260271 0.114446074   255 0 77 255   0.73317087 0.095917225   
              0.25214583 0.027201744 -0.096916676   0.24877454 1.7481252 -0.24926557   255 0 77 255   0.24732429 0.6690415   
              0.16371037 0.4742977 -0.132104   -1.6347535 0.6950559 0.15633382   255 0 77 255   0.04949457 0.55558026   
              0.46774322 0.05171531 -0.17505376   -0.14210583 1.7750423 0.09483968   255 0 77 255   0.04949457 0.55558026
            </Data>
          </VertexBuffer>
          <IndexBuffer>
            <Data>
              0 1 2 3 4 5 6 7 8 3 7 9 10 3 5 8 0 2 8 11 6 12 13 14 
              15 16 17 18 19 20 15 19 21 22 15 17 20 23 12 20 24 18 25 26 27 28 29 30 
              31 32 33 34 35 36 37 38 39 40 41 42 43 44 45 46 47 48 49 50 51 52 53 54 
              49 53 55 56 49 51 54 57 46 54 58 52 59 60 61 62 63 64 65 66 67 68 69 70 
              71 72 73 74 75 76 77 78 79 80 81 82 83 84 85 86 87 88 89 90 91 92 93 94 
              95 96 97 98 99 100 101 102 103 104 105 106 107 108 109 110 111 112 113 104 106 114 115 116 
              117 118 119 120 121 122 123 124 125 126 127 128 123 127 129 130 123 125 128 120 122 128 131 126 
              132 133 134 135 136 137 138 139 140 135 139 141 142 135 137 140 132 134 140 143 138 0 144 1 
              6 9 7 3 10 7 8 2 11 12 23 13 18 21 19 15 22 19 20 12 24 25 145 26 
              31 146 32 34 147 35 43 148 44 46 57 47 52 55 53 49 56 53 54 46 58 59 149 60 
              65 150 66 68 151 69 77 152 78 80 153 81 86 154 87 89 155 90 98 156 99 101 157 102 
              107 158 108 110 159 111 117 160 118 120 161 121 126 129 127 123 130 127 128 122 131 132 162 133 
              138 141 139 135 142 139 140 134 143
            </Data>
          </IndexBuffer>
        </Item>
      </Geometries>
    </Item>
  </DrawableModelsHigh>
  <Bounds type="Composite">
    <BoxMin x="-0.60239536" y="-0.575938" z="-0.44816014" />
    <BoxMax x="0.57881224" y="0.58196396" z="0.574673" />
    <BoxCenter x="-0.011791557" y="0.003012985" z="0.06325643" />
    <SphereCenter x="-0.011791557" y="0.003012985" z="0.06325643" />
    <SphereRadius value="0.9723909" />
    <Margin value="0" />
    <Volume value="0" />
    <Inertia x="0.0" y="0.0" z="0.0" />
    <MaterialIndex value="0" />
    <MaterialColourIndex value="0" />
    <ProceduralID value="0" />
    <RoomID value="0" />
    <PedDensity value="0" />
    <UnkFlags value="0" />
    <PolyFlags value="0" />
    <UnkType value="1" />
    <Children>
      <Item type="GeometryBVH">
        <BoxMin x="-0.60239536" y="-0.575938" z="-0.44816014" />
        <BoxMax x="0.57881224" y="0.58196396" z="0.574673" />
        <BoxCenter x="-0.011791557" y="0.003012985" z="0.06325643" />
        <SphereCenter x="-0.011791557" y="0.003012985" z="0.06325643" />
        <SphereRadius value="0.9723909" />
        <Margin value="0" />
        <Volume value="0" />
        <Inertia x="0.0" y="0.0" z="0.0" />
        <MaterialIndex value="0" />
        <MaterialColourIndex value="0" />
        <ProceduralID value="0" />
        <RoomID value="0" />
        <PedDensity value="0" />
        <UnkFlags value="0" />
        <PolyFlags value="0" />
        <UnkType value="1" />
        <CompositeTransform>
          1.0 0.0 0.0 0.0
          0.0 1.0 0.0 0.0
          0.0 0.0 1.0 0.0
          0.0 0.0 0.0 1.0
        </CompositeTransform>
        <CompositeFlags1>FOLIAGE, PLANT</CompositeFlags1>
        <CompositeFlags2>ANIMAL, ANIMAL_RAGDOLL, EXPLOSION, FORKLIFT_FORKS, GLASS, MAP_DYNAMIC, OBJECT, PED, PROJECTILE, RAGDOLL, TEST_AI, TEST_CAMERA, TEST_SCRIPT, TEST_WEAPON, VEHICLE_BVH, VEHICLE_NOT_BVH</CompositeFlags2>
        <GeometryCenter x="-0.011791557" y="0.003012985" z="0.06325643" />
        <Materials>
          <Item>
            <Type value="0" />
            <ProceduralID value="0" />
            <RoomID value="0" />
            <PedDensity value="0" />
            <MaterialColourIndex value="0" />
            <Unk value="0" />
          </Item>
        </Materials>
        <Vertices>
          0.1542540043592453, -0.20748133957386017, -0.29190608859062195
          0.26513543725013733, -0.3305659294128418, -0.11575417220592499
          0.30193910002708435, -0.3792398273944855, -0.24665780365467072
          0.2916778326034546, -0.3681453764438629, -0.2701749801635742
          -0.19659292697906494, 0.20688866078853607, -0.2458142340183258
          -0.3285631239414215, 0.3664511740207672, -0.13896210491657257
          -0.2422798126935959, 0.27043259143829346, -0.007651385851204395
          0.011379231698811054, -0.046524468809366226, -0.46171557903289795
          -0.09211746603250504, 0.07571110129356384, -0.44811904430389404
          -0.07334118336439133, 0.07254742085933685, 0.009939535520970821
          0.07174691557884216, -0.09757467359304428, 0.020716987550258636
          -0.1741800457239151, 0.19280938804149628, 0.05136781930923462
          0.06513815373182297, -0.10620220005512238, -0.3763447403907776
          0.22653613984584808, 0.14639300107955933, -0.15156230330467224
          0.38317418098449707, 0.2049722671508789, 0.2020924687385559
          0.4260498881340027, 0.2531120479106903, -0.05357618257403374
          0.4116785526275635, 0.2484864890575409, -0.09424121677875519
          -0.2436065822839737, -0.12816199660301208, -0.12911289930343628
          -0.4182266294956207, -0.24369513988494873, 0.02809053659439087
          -0.295745313167572, -0.19778650999069214, 0.3034304082393646
          0.030385278165340424, 0.060409996658563614, -0.45580580830574036
          -0.10830555111169815, -0.020579330623149872, -0.4491829574108124
          -0.0683729276061058, -0.07103271037340164, 0.35873544216156006
          0.12679149210453033, 0.0384259968996048, 0.39903801679611206
          -0.20279549062252045, -0.15379860997200012, 0.41201913356781006
          0.10472603887319565, 0.08982300758361816, -0.30563801527023315
          -0.11368509382009506, -0.28333228826522827, -0.14913620054721832
          0.03534580022096634, -0.43437543511390686, 0.19834886491298676
          0.015558210201561451, -0.4941060543060303, -0.05770428478717804
          0.012583336792886257, -0.4791165590286255, -0.0982995331287384
          -0.015318494290113449, 0.2648196518421173, -0.12771153450012207
          -0.001944056712090969, 0.4728993773460388, 0.030644705519080162
          0.01799226924777031, 0.3422945737838745, 0.30535638332366943
          -0.042386800050735474, -0.06485958397388458, -0.45625224709510803
          -0.04075456038117409, 0.09570182114839554, -0.44876861572265625
          0.020349344238638878, 0.0816948264837265, 0.3592797815799713
          0.02182237058877945, -0.1422722190618515, 0.398393839597702
          0.07516486942768097, 0.23934464156627655, 0.416161447763443
          -0.03157385438680649, -0.14480511844158173, -0.3064742684364319
          0.09318529069423676, 0.264250785112381, -0.1359216272830963
          0.175895094871521, 0.3873279094696045, 0.18220748007297516
          0.18829813599586487, 0.4632464349269867, -0.02569011226296425
          0.18006929755210876, 0.4531981647014618, -0.06707530468702316
          -0.12054836004972458, -0.23692379891872406, -0.14354638755321503
          -0.19383414089679718, -0.4420205056667328, 0.0017714612185955048
          -0.12993507087230682, -0.34518033266067505, 0.2397860735654831
          -0.008843710646033287, 0.09507868438959122, -0.451204776763916
          -0.07189375907182693, -0.05276426672935486, -0.4534538686275482
          -0.02385386824607849, -0.11122162640094757, 0.30931705236434937
          0.06690862774848938, 0.09050710499286652, 0.3618648052215576
          -0.08304134011268616, -0.26048487424850464, 0.3537762761116028
          0.031255099922418594, 0.15475963056087494, -0.2970205545425415
          0.1043626070022583, -0.2511310875415802, -0.16118180751800537
          0.19629737734794617, -0.40309420228004456, 0.1873786449432373
          0.2082260400056839, -0.45564669370651245, -0.07072696089744568
          0.19948527216911316, -0.4419627785682678, -0.11094921082258224
          -0.13086897134780884, 0.23867356777191162, -0.1202356368303299
          -0.21264484524726868, 0.4252232313156128, 0.0442766398191452
          -0.21270351111888885, 0.24843916296958923, 0.3109135031700134
          -0.005553622730076313, -0.0565236359834671, -0.45863521099090576
          -0.0749446302652359, 0.08796674013137817, -0.4465565085411072
          -0.024557286873459816, 0.07153423130512238, 0.36218518018722534
          0.09750108420848846, -0.10624464601278305, 0.3994830846786499
          -0.16194921731948853, 0.15511393547058105, 0.41617870330810547
          0.03741281479597092, -0.1291954219341278, -0.3109375834465027
          0.2031324952840805, -0.17188698053359985, -0.16487658023834229
          0.3627278804779053, -0.25173187255859375, 0.23065285384655
          0.3961794972419739, -0.28201839327812195, -0.07477717101573944
          0.38288870453834534, -0.2719801962375641, -0.11482898890972137
          -0.2220105677843094, 0.1655460000038147, -0.11682640016078949
          -0.37884870171546936, 0.2918773591518402, 0.05049402266740799
          -0.24570493400096893, 0.266244113445282, 0.3704458773136139
          0.023501520976424217, -0.03321292623877525, -0.4597221314907074
          -0.10191456228494644, 0.06632458418607712, -0.44554781913757324
          -0.10167258977890015, 0.032121751457452774, 0.40113958716392517
          0.1455848664045334, -0.05732683092355728, 0.4449576437473297
          -0.1777009665966034, 0.13771171867847443, 0.4706937074661255
          0.09183219075202942, -0.08553427457809448, -0.312973290681839
          0.263937383890152, 0.024188758805394173, -0.16017310321331024
          0.4260311424732208, -5.8465637266635895e-05, 0.12456674873828888
          0.4927368760108948, 0.035234883427619934, -0.06892824172973633
          0.4766465425491333, 0.036239221692085266, -0.10919637978076935
          -0.29774221777915955, -0.049510229378938675, -0.11929421871900558
          -0.5007849931716919, -0.07218384742736816, 0.04445209726691246
          -0.3675037622451782, -0.07397009432315826, 0.2538919448852539
          0.04138674587011337, 0.024465350434184074, -0.4583384394645691
          -0.11851783841848373, 0.012784920632839203, -0.4468321204185486
          -0.08648670464754105, -0.024252405390143394, 0.29949134588241577
          0.12563717365264893, 0.11400299519300461, 0.33167564868927
          -0.2616320252418518, -0.07219383120536804, 0.3595063388347626
          0.12533439695835114, 0.022494938224554062, -0.3103819787502289
          0.08364047855138779, 0.27024659514427185, -0.26248040795326233
          0.15675854682922363, 0.39934906363487244, -0.07153230905532837
          0.17550194263458252, 0.4712847173213959, -0.19536040723323822
          0.1685236543416977, 0.4604508876800537, -0.22016409039497375
          -0.13009312748908997, -0.2309279888868332, -0.27010461688041687
          -0.2078809142112732, -0.43319663405418396, -0.18448089063167572
          -0.15115587413311005, -0.3318498730659485, -0.04159059375524521
          -0.008904293179512024, 0.0951167419552803, -0.45200806856155396
          -0.07195433974266052, -0.05272621288895607, -0.45425716042518616
          -0.047075510025024414, -0.09663428366184235, 0.0014103481080383062
          0.042186349630355835, 0.10603711009025574, 0.03406060114502907
          -0.10768024623394012, -0.2450072467327118, 0.027077430859208107
          0.02654578909277916, 0.15771791338920593, -0.35946333408355713
          0.2541648745536804, 0.033232431858778, -0.2865697741508484
          0.41759762167930603, 0.03680166229605675, -0.1083802729845047
          0.479534775018692, 0.04870232939720154, -0.23831018805503845
          0.46470412611961365, 0.04878103733062744, -0.2620052099227905
          -0.28745728731155396, -0.012207805179059505, -0.24787446856498718
          -0.4948252737522125, -0.03436514362692833, -0.1439451277256012
          -0.3674173653125763, -0.031263358891010284, -0.01104002632200718
          0.041258279234170914, 0.025398198515176773, -0.45909422636032104
          -0.11851513385772705, 0.011991744861006737, -0.4476795494556427
          -0.10823077708482742, -0.011634401977062225, 0.010049501433968544
          0.11453735083341599, 0.005469434428960085, 0.023839008063077927
          -0.2650443911552429, -0.02628706954419613, 0.04930758476257324
          0.12049850821495056, 0.0271286740899086, -0.372735857963562
        </Vertices>
        <VertexColours>
          255, 255, 255, 255
          255, 255, 255, 255
          255, 255, 255, 255
          255, 255, 255, 255
          255, 255, 255, 255
          255, 255, 255, 255
          255, 255, 255, 255
          255, 255, 255, 255
          255, 255, 255, 255
          255, 255, 255, 255
          255, 255, 255, 255
          255, 255, 255, 255
          255, 255, 255, 255
          255, 255, 255, 255
          255, 255, 255, 255
          255, 255, 255, 255
          255, 255, 255, 255
          255, 255, 255, 255
          255, 255, 255, 255
          255, 255, 255, 255
          255, 255, 255, 255
          255, 255, 255, 255
          255, 255, 255, 255
          255, 255, 255, 255
          255, 255, 255, 255
          255, 255, 255, 255
          255, 255, 255, 255
          255, 255, 255, 255
          255, 255, 255, 255
          255, 255, 255, 255
          255, 255, 255, 255
          255, 255, 255, 255
          255, 255, 255, 255
          255, 255, 255, 255
          255, 255, 255, 255
          255, 255, 255, 255
          255, 255, 255, 255
          255, 255, 255, 255
          255, 255, 255, 255
          255, 255, 255, 255
          255, 255, 255, 255
          255, 255, 255, 255
          255, 255, 255, 255
          255, 255, 255, 255
          255, 255, 255, 255
          255, 255, 255, 255
          255, 255, 255, 255
          255, 255, 255, 255
          255, 255, 255, 255
          255, 255, 255, 255
          255, 255, 255, 255
          255, 255, 255, 255
          255, 255, 255, 255
          255, 255, 255, 255
          255, 255, 255, 255
          255, 255, 255, 255
          255, 255, 255, 255
          255, 255, 255, 255
          255, 255, 255, 255
          255, 255, 255, 255
          255, 255, 255, 255
          255, 255, 255, 255
          255, 255, 255, 255
          255, 255, 255, 255
          255, 255, 255, 255
          255, 255, 255, 255
          255, 255, 255, 255
          255, 255, 255, 255
          255, 255, 255, 255
          255, 255, 255, 255
          255, 255, 255, 255
          255, 255, 255, 255
          255, 255, 255, 255
          255, 255, 255, 255
          255, 255, 255, 255
          255, 255, 255, 255
          255, 255, 255, 255
          255, 255, 255, 255
          255, 255, 255, 255
          255, 255, 255, 255
          255, 255, 255, 255
          255, 255, 255, 255
          255, 255, 255, 255
          255, 255, 255, 255
          255, 255, 255, 255
          255, 255, 255, 255
          255, 255, 255, 255
          255, 255, 255, 255
          255, 255, 255, 255
          255, 255, 255, 255
          255, 255, 255, 255
          255, 255, 255, 255
          255, 255, 255, 255
          255, 255, 255, 255
          255, 255, 255, 255
          255, 255, 255, 255
          255, 255, 255, 255
          255, 255, 255, 255
          255, 255, 255, 255
          255, 255, 255, 255
          255, 255, 255, 255
          255, 255, 255, 255
          255, 255, 255, 255
          255, 255, 255, 255
          255, 255, 255, 255
          255, 255, 255, 255
          255, 255, 255, 255
          255, 255, 255, 255
          255, 255, 255, 255
          255, 255, 255, 255
          255, 255, 255, 255
          255, 255, 255, 255
          255, 255, 255, 255
          255, 255, 255, 255
          255, 255, 255, 255
          255, 255, 255, 255
          255, 255, 255, 255
          255, 255, 255, 255
          255, 255, 255, 255
          255, 255, 255, 255
          255, 255, 255, 255
          255, 255, 255, 255
          255, 255, 255, 255
          255, 255, 255, 255
          255, 255, 255, 255
          255, 255, 255, 255
          255, 255, 255, 255
          255, 255, 255, 255
          255, 255, 255, 255
          255, 255, 255, 255
          255, 255, 255, 255
          255, 255, 255, 255
          255, 255, 255, 255
          255, 255, 255, 255
          255, 255, 255, 255
          255, 255, 255, 255
          255, 255, 255, 255
          255, 255, 255, 255
          255, 255, 255, 255
          255, 255, 255, 255
          255, 255, 255, 255
          255, 255, 255, 255
          255, 255, 255, 255
          255, 255, 255, 255
          255, 255, 255, 255
          255, 255, 255, 255
          255, 255, 255, 255
          255, 255, 255, 255
          255, 255, 255, 255
          255, 255, 255, 255
          255, 255, 255, 255
          255, 255, 255, 255
          255, 255, 255, 255
          255, 255, 255, 255
          255, 255, 255, 255
          255, 255, 255, 255
          255, 255, 255, 255
          255, 255, 255, 255
          255, 255, 255, 255
          255, 255, 255, 255
          255, 255, 255, 255
          255, 255, 255, 255
          255, 255, 255, 255
          255, 255, 255, 255
          255, 255, 255, 255
          255, 255, 255, 255
          255, 255, 255, 255
          255, 255, 255, 255
          255, 255, 255, 255
          255, 255, 255, 255
          255, 255, 255, 255
          255, 255, 255, 255
          255, 255, 255, 255
          255, 255, 255, 255
          255, 255, 255, 255
          255, 255, 255, 255
          255, 255, 255, 255
          255, 255, 255, 255
          255, 255, 255, 255
          255, 255, 255, 255
          255, 255, 255, 255
          255, 255, 255, 255
          255, 255, 255, 255
          255, 255, 255, 255
          255, 255, 255, 255
          255, 255, 255, 255
          255, 255, 255, 255
          255, 255, 255, 255
          255, 255, 255, 255
          255, 255, 255, 255
          255, 255, 255, 255
          255, 255, 255, 255
          255, 255, 255, 255
          255, 255, 255, 255
          255, 255, 255, 255
          255, 255, 255, 255
          255, 255, 255, 255
          255, 255, 255, 255
          255, 255, 255, 255
          255, 255, 255, 255
          255, 255, 255, 255
          255, 255, 255, 255
          255, 255, 255, 255
          255, 255, 255, 255
          255, 255, 255, 255
          255, 255, 255, 255
          255, 255, 255, 255
          255, 255, 255, 255
          255, 255, 255, 255
          255, 255, 255, 255
          255, 255, 255, 255
          255, 255, 255, 255
          255, 255, 255, 255
          255, 255, 255, 255
          255, 255, 255, 255
          255, 255, 255, 255
          255, 255, 255, 255
          255, 255, 255, 255
          255, 255, 255, 255
          255, 255, 255, 255
          255, 255, 255, 255
          255, 255, 255, 255
          255, 255, 255, 255
          255, 255, 255, 255
          255, 255, 255, 255
        </VertexColours>
        <Polygons>
          <Triangle m="0" v1="0" v2="1" v3="2" f1="0" f2="0" f3="0" />
          <Triangle m="0" v1="0" v2="2" v3="3" f1="0" f2="0" f3="0" />
          <Triangle m="0" v1="4" v2="5" v3="6" f1="0" f2="0" f3="0" />
          <Triangle m="0" v1="7" v2="8" v3="9" f1="0" f2="0" f3="0" />
          <Triangle m="0" v1="7" v2="9" v3="10" f1="0" f2="0" f3="0" />
          <Triangle m="0" v1="8" v2="4" v3="11" f1="0" f2="0" f3="0" />
          <Triangle m="0" v1="8" v2="11" v3="9" f1="0" f2="0" f3="0" />
          <Triangle m="0" v1="11" v2="4" v3="6" f1="0" f2="0" f3="0" />
          <Triangle m="0" v1="10" v2="1" v3="0" f1="0" f2="0" f3="0" />
          <Triangle m="0" v1="7" v2="10" v3="12" f1="0" f2="0" f3="0" />
          <Triangle m="0" v1="10" v2="0" v3="12" f1="0" f2="0" f3="0" />
          <Triangle m="0" v1="13" v2="14" v3="15" f1="0" f2="0" f3="0" />
          <Triangle m="0" v1="13" v2="15" v3="16" f1="0" f2="0" f3="0" />
          <Triangle m="0" v1="17" v2="18" v3="19" f1="0" f2="0" f3="0" />
          <Triangle m="0" v1="20" v2="21" v3="22" f1="0" f2="0" f3="0" />
          <Triangle m="0" v1="20" v2="22" v3="23" f1="0" f2="0" f3="0" />
          <Triangle m="0" v1="21" v2="17" v3="24" f1="0" f2="0" f3="0" />
          <Triangle m="0" v1="21" v2="24" v3="22" f1="0" f2="0" f3="0" />
          <Triangle m="0" v1="24" v2="17" v3="19" f1="0" f2="0" f3="0" />
          <Triangle m="0" v1="23" v2="14" v3="13" f1="0" f2="0" f3="0" />
          <Triangle m="0" v1="20" v2="23" v3="25" f1="0" f2="0" f3="0" />
          <Triangle m="0" v1="23" v2="13" v3="25" f1="0" f2="0" f3="0" />
          <Triangle m="0" v1="26" v2="27" v3="28" f1="0" f2="0" f3="0" />
          <Triangle m="0" v1="26" v2="28" v3="29" f1="0" f2="0" f3="0" />
          <Triangle m="0" v1="30" v2="31" v3="32" f1="0" f2="0" f3="0" />
          <Triangle m="0" v1="33" v2="34" v3="35" f1="0" f2="0" f3="0" />
          <Triangle m="0" v1="33" v2="35" v3="36" f1="0" f2="0" f3="0" />
          <Triangle m="0" v1="34" v2="30" v3="37" f1="0" f2="0" f3="0" />
          <Triangle m="0" v1="34" v2="37" v3="35" f1="0" f2="0" f3="0" />
          <Triangle m="0" v1="37" v2="30" v3="32" f1="0" f2="0" f3="0" />
          <Triangle m="0" v1="36" v2="27" v3="26" f1="0" f2="0" f3="0" />
          <Triangle m="0" v1="33" v2="36" v3="38" f1="0" f2="0" f3="0" />
          <Triangle m="0" v1="36" v2="26" v3="38" f1="0" f2="0" f3="0" />
          <Triangle m="0" v1="39" v2="40" v3="41" f1="0" f2="0" f3="0" />
          <Triangle m="0" v1="39" v2="41" v3="42" f1="0" f2="0" f3="0" />
          <Triangle m="0" v1="43" v2="44" v3="45" f1="0" f2="0" f3="0" />
          <Triangle m="0" v1="46" v2="47" v3="48" f1="0" f2="0" f3="0" />
          <Triangle m="0" v1="46" v2="48" v3="49" f1="0" f2="0" f3="0" />
          <Triangle m="0" v1="47" v2="43" v3="50" f1="0" f2="0" f3="0" />
          <Triangle m="0" v1="47" v2="50" v3="48" f1="0" f2="0" f3="0" />
          <Triangle m="0" v1="50" v2="43" v3="45" f1="0" f2="0" f3="0" />
          <Triangle m="0" v1="49" v2="40" v3="39" f1="0" f2="0" f3="0" />
          <Triangle m="0" v1="46" v2="49" v3="51" f1="0" f2="0" f3="0" />
          <Triangle m="0" v1="49" v2="39" v3="51" f1="0" f2="0" f3="0" />
          <Triangle m="0" v1="52" v2="53" v3="54" f1="0" f2="0" f3="0" />
          <Triangle m="0" v1="52" v2="54" v3="55" f1="0" f2="0" f3="0" />
          <Triangle m="0" v1="56" v2="57" v3="58" f1="0" f2="0" f3="0" />
          <Triangle m="0" v1="59" v2="60" v3="61" f1="0" f2="0" f3="0" />
          <Triangle m="0" v1="59" v2="61" v3="62" f1="0" f2="0" f3="0" />
          <Triangle m="0" v1="60" v2="56" v3="63" f1="0" f2="0" f3="0" />
          <Triangle m="0" v1="60" v2="63" v3="61" f1="0" f2="0" f3="0" />
          <Triangle m="0" v1="63" v2="56" v3="58" f1="0" f2="0" f3="0" />
          <Triangle m="0" v1="62" v2="53" v3="52" f1="0" f2="0" f3="0" />
          <Triangle m="0" v1="59" v2="62" v3="64" f1="0" f2="0" f3="0" />
          <Triangle m="0" v1="62" v2="52" v3="64" f1="0" f2="0" f3="0" />
          <Triangle m="0" v1="65" v2="66" v3="67" f1="0" f2="0" f3="0" />
          <Triangle m="0" v1="65" v2="67" v3="68" f1="0" f2="0" f3="0" />
          <Triangle m="0" v1="69" v2="70" v3="71" f1="0" f2="0" f3="0" />
          <Triangle m="0" v1="72" v2="73" v3="74" f1="0" f2="0" f3="0" />
          <Triangle m="0" v1="72" v2="74" v3="75" f1="0" f2="0" f3="0" />
          <Triangle m="0" v1="73" v2="69" v3="76" f1="0" f2="0" f3="0" />
          <Triangle m="0" v1="73" v2="76" v3="74" f1="0" f2="0" f3="0" />
          <Triangle m="0" v1="76" v2="69" v3="71" f1="0" f2="0" f3="0" />
          <Triangle m="0" v1="75" v2="66" v3="65" f1="0" f2="0" f3="0" />
          <Triangle m="0" v1="72" v2="75" v3="77" f1="0" f2="0" f3="0" />
          <Triangle m="0" v1="75" v2="65" v3="77" f1="0" f2="0" f3="0" />
          <Triangle m="0" v1="78" v2="79" v3="80" f1="0" f2="0" f3="0" />
          <Triangle m="0" v1="78" v2="80" v3="81" f1="0" f2="0" f3="0" />
          <Triangle m="0" v1="82" v2="83" v3="84" f1="0" f2="0" f3="0" />
          <Triangle m="0" v1="85" v2="86" v3="87" f1="0" f2="0" f3="0" />
          <Triangle m="0" v1="85" v2="87" v3="88" f1="0" f2="0" f3="0" />
          <Triangle m="0" v1="86" v2="82" v3="89" f1="0" f2="0" f3="0" />
          <Triangle m="0" v1="86" v2="89" v3="87" f1="0" f2="0" f3="0" />
          <Triangle m="0" v1="89" v2="82" v3="84" f1="0" f2="0" f3="0" />
          <Triangle m="0" v1="88" v2="79" v3="78" f1="0" f2="0" f3="0" />
          <Triangle m="0" v1="85" v2="88" v3="90" f1="0" f2="0" f3="0" />
          <Triangle m="0" v1="88" v2="78" v3="90" f1="0" f2="0" f3="0" />
          <Triangle m="0" v1="91" v2="92" v3="93" f1="0" f2="0" f3="0" />
          <Triangle m="0" v1="91" v2="93" v3="94" f1="0" f2="0" f3="0" />
          <Triangle m="0" v1="95" v2="96" v3="97" f1="0" f2="0" f3="0" />
          <Triangle m="0" v1="98" v2="99" v3="100" f1="0" f2="0" f3="0" />
          <Triangle m="0" v1="98" v2="100" v3="101" f1="0" f2="0" f3="0" />
          <Triangle m="0" v1="99" v2="95" v3="102" f1="0" f2="0" f3="0" />
          <Triangle m="0" v1="99" v2="102" v3="100" f1="0" f2="0" f3="0" />
          <Triangle m="0" v1="102" v2="95" v3="97" f1="0" f2="0" f3="0" />
          <Triangle m="0" v1="101" v2="92" v3="91" f1="0" f2="0" f3="0" />
          <Triangle m="0" v1="98" v2="101" v3="103" f1="0" f2="0" f3="0" />
          <Triangle m="0" v1="101" v2="91" v3="103" f1="0" f2="0" f3="0" />
          <Triangle m="0" v1="104" v2="105" v3="106" f1="0" f2="0" f3="0" />
          <Triangle m="0" v1="104" v2="106" v3="107" f1="0" f2="0" f3="0" />
          <Triangle m="0" v1="108" v2="109" v3="110" f1="0" f2="0" f3="0" />
          <Triangle m="0" v1="111" v2="112" v3="113" f1="0" f2="0" f3="0" />
          <Triangle m="0" v1="111" v2="113" v3="114" f1="0" f2="0" f3="0" />
          <Triangle m="0" v1="112" v2="108" v3="115" f1="0" f2="0" f3="0" />
          <Triangle m="0" v1="112" v2="115" v3="113" f1="0" f2="0" f3="0" />
          <Triangle m="0" v1="115" v2="108" v3="110" f1="0" f2="0" f3="0" />
          <Triangle m="0" v1="114" v2="105" v3="104" f1="0" f2="0" f3="0" />
          <Triangle m="0" v1="111" v2="114" v3="116" f1="0" f2="0" f3="0" />
          <Triangle m="0" v1="114" v2="104" v3="116" f1="0" f2="0" f3="0" />
        </Polygons>
      </Item>
    </Children>
  </Bounds>
</Drawable>
